[
  {
    "account_id": "31337x.31337.betanet",
    "public_key": "ed25519:Fq3nCAgvtuKnudDoJ6BiDmnUT4jPqMqGZ8KXCpbkncjB",
    "is_slashed": false,
    "stake": "122434397771140766470860352619",
    "shards": [
      0
    ],
    "num_produced_blocks": 99,
    "num_expected_blocks": 100
  },
  {
    "account_id": "40th.meridian.betanet",
    "public_key": "ed25519:5473fp2JRx69GAA6KLbaeJo2F7NsPwV9ywqEKrDjJwV4",
    "is_slashed": false,
    "stake": "85815581299188144857459603860",
    "shards": [
      0
    ],
    "num_produced_blocks": 96,
    "num_expected_blocks": 100
  },
  {
    "account_id": "777stakes",
    "public_key": "ed25519:A8dkaqFGB5tzr6Yfb2fXksiS5KYDU1wJszRPtvWTMSMS",
    "is_slashed": false,
    "stake": "138665111043007777016674290445",
    "shards": [
      0
    ],
    "num_produced_blocks": 199,
    "num_expected_blocks": 200
  },
  {
    "account_id": "a_validator",
    "public_key": "ed25519:4LqT2m4WmZFDkRxMrRwAg7cnE4jEfzrAdNWqRcCWxgfY",
    "is_slashed": false,
    "stake": "211649666272024328659027912929",
    "shards": [
      0
    ],
    "num_produced_blocks": 298,
    "num_expected_blocks": 300
  },
  {
    "account_id": "ag_staking",
    "public_key": "ed25519:5RFyRfrUetiG4bxmWKtRqbXtDtT2acngUBZYrCXk2Mja",
    "is_slashed": false,
    "stake": "105292126998448362211559011610",
    "shards": [
      0
    ],
    "num_produced_blocks": 99,
    "num_expected_blocks": 100
  },
  {
    "account_id": "alive29",
    "public_key": "ed25519:8qDFejq6yrEfH8edasrYjrtRJTr3s9kq1NMKX3U1XKAa",
    "is_slashed": false,
    "stake": "130517360359611920359296265061",
    "shards": [
      0
    ],
    "num_produced_blocks": 198,
    "num_expected_blocks": 200
  },
  {
    "account_id": "anonstake",
    "public_key": "ed25519:6Q6GTPhSiYHuKQD2BjWhNXCCBcBZMVUwZTG5EKczur4S",
    "is_slashed": false,
    "stake": "131086083440212336749417188106",
    "shards": [
      0
    ],
    "num_produced_blocks": 194,
    "num_expected_blocks": 200
  },
  {
    "account_id": "aptemuyc4",
    "public_key": "ed25519:Dzcdmjxo6wqD8vHgxkGM7wccXrxcWpCpZ6JzrPvr5KZy",
    "is_slashed": false,
    "stake": "114705354724287354567937945913",
    "shards": [
      0
    ],
    "num_produced_blocks": 89,
    "num_expected_blocks": 100
  },
  {
    "account_id": "arm.armada.betanet",
    "public_key": "ed25519:3qTS2RhbfnExZCUoJSAt4frtie4LSQiS9uuuncSkY8Nv",
    "is_slashed": false,
    "stake": "85737701829516821523914851706",
    "shards": [
      0
    ],
    "num_produced_blocks": 99,
    "num_expected_blocks": 100
  },
  {
    "account_id": "averonix",
    "public_key": "ed25519:4Je5ZNRHW6usvkNi1coviAAbeFCct7qLTjCriWFP8Ua1",
    "is_slashed": false,
    "stake": "116866936643122496958158418564",
    "shards": [
      0
    ],
    "num_produced_blocks": 98,
    "num_expected_blocks": 100
  },
  {
    "account_id": "bi23.betanet",
    "public_key": "ed25519:4vHcYPdBBS33CucaaXd6fokiQQctt8dULctswiBGvCb4",
    "is_slashed": false,
    "stake": "75243800885920821958912054777",
    "shards": [
      0
    ],
    "num_produced_blocks": 98,
    "num_expected_blocks": 100
  },
  {
    "account_id": "bitcat.stakehouse.betanet",
    "public_key": "ed25519:FpLUTtw7Se3mZHPLG3ZNbwNbK9k3xDxeCc9pR7fWxkKT",
    "is_slashed": false,
    "stake": "152494249637154025407612744749",
    "shards": [
      0
    ],
    "num_produced_blocks": 200,
    "num_expected_blocks": 200
  },
  {
    "account_id": "blink",
    "public_key": "ed25519:GZGBTHvnhJNp87ZaZ7CiGJZi53SruYLdNj5SVMya9p2w",
    "is_slashed": false,
    "stake": "115680937101120774629306070380",
    "shards": [
      0
    ],
    "num_produced_blocks": 93,
    "num_expected_blocks": 100
  },
  {
    "account_id": "bucket",
    "public_key": "ed25519:6TCBt4yLU6m4KKPPiVX9NumZuHEB5aPcNRJoLrUecg4w",
    "is_slashed": false,
    "stake": "129314494175971157206896259519",
    "shards": [
      0
    ],
    "num_produced_blocks": 0,
    "num_expected_blocks": 200
  },
  {
    "account_id": "c1.hashquark",
    "public_key": "ed25519:8zohSr8u46tHfGuP8Y9fp5Gu2h4CdtCJPeSHSHSjZta",
    "is_slashed": false,
    "stake": "91459177567926561205688498878",
    "shards": [
      0
    ],
    "num_produced_blocks": 101,
    "num_expected_blocks": 101
  },
  {
    "account_id": "cloudpost_pool",
    "public_key": "ed25519:AVVLmJDG8z6UgmW9fmJGVFTdYxxfnqXH6c7FVQmhE6dp",
    "is_slashed": false,
    "stake": "116930065935561922220205863896",
    "shards": [
      0
    ],
    "num_produced_blocks": 99,
    "num_expected_blocks": 100
  },
  {
    "account_id": "contract.nats.betanet",
    "public_key": "ed25519:Cnyg637j9J21HYH9ey5Gm9H25MkfQaN94DQVYsykAdJi",
    "is_slashed": false,
    "stake": "84142493315489541356824984606",
    "shards": [
      0
    ],
    "num_produced_blocks": 0,
    "num_expected_blocks": 101
  },
  {
    "account_id": "delight_pool",
    "public_key": "ed25519:6XDV4Q4HZPFNdsmc2g8b77MSp19pbooeSSsdufupXRKH",
    "is_slashed": false,
    "stake": "113382289390967685915807604996",
    "shards": [
      0
    ],
    "num_produced_blocks": 98,
    "num_expected_blocks": 100
  },
  {
    "account_id": "dochpryof",
    "public_key": "ed25519:Fao69e1AsMWZru7wckTapjZhNJhN7CsJ5ZbzPFTfoka8",
    "is_slashed": false,
    "stake": "124107539077077022259300923377",
    "shards": [
      0
    ],
    "num_produced_blocks": 195,
    "num_expected_blocks": 201
  },
  {
    "account_id": "dog.bears.betanet",
    "public_key": "ed25519:8x2zfo7QksoJ77iLEkYHzhvQnUAJ97WCC7BijWUDfe3N",
    "is_slashed": false,
    "stake": "113217719178242648936223168890",
    "shards": [
      0
    ],
    "num_produced_blocks": 92,
    "num_expected_blocks": 100
  },
  {
    "account_id": "felixschulz",
    "public_key": "ed25519:E9wRngygkNQNfQLMJjkztaLiesckPoVdFPddGhqvGudn",
    "is_slashed": false,
    "stake": "119790183733452104340718908580",
    "shards": [
      0
    ],
    "num_produced_blocks": 100,
    "num_expected_blocks": 100
  },
  {
    "account_id": "fredrik_pool",
    "public_key": "ed25519:812BZ452dc5TYnK3SuVBzDWBahG5fRobST36acHVhHK5",
    "is_slashed": false,
    "stake": "120016256305312553718377529557",
    "shards": [
      0
    ],
    "num_produced_blocks": 99,
    "num_expected_blocks": 100
  },
  {
    "account_id": "gems",
    "public_key": "ed25519:84UPBh7a8z2CMEy6HmJFAphfQfdMGcXoukNeoNgTVnFM",
    "is_slashed": false,
    "stake": "94554089789021954005363870736",
    "shards": [
      0
    ],
    "num_produced_blocks": 97,
    "num_expected_blocks": 100
  },
  {
    "account_id": "get_rich",
    "public_key": "ed25519:ARoCgrjV6Q86wFWEyMag6ygcAVZoBBrorJq7GsZEaWtL",
    "is_slashed": false,
    "stake": "187204183793604567272251677285",
    "shards": [
      0
    ],
    "num_produced_blocks": 108,
    "num_expected_blocks": 300
  },
  {
    "account_id": "huglester",
    "public_key": "ed25519:EHW7tfitm8n2gdV1MzsXBUJMfdbsdxaZMKXx5xJS7Fah",
    "is_slashed": false,
    "stake": "213660889943201603266378028217",
    "shards": [
      0
    ],
    "num_produced_blocks": 292,
    "num_expected_blocks": 300
  },
  {
    "account_id": "isillien",
    "public_key": "ed25519:45CJTQuuUUi2bXWuBpJsas7rPibNtgVt2W5uCNfTgJiH",
    "is_slashed": false,
    "stake": "118888748816878446646820632276",
    "shards": [
      0
    ],
    "num_produced_blocks": 98,
    "num_expected_blocks": 100
  },
  {
    "account_id": "janliamnilsson",
    "public_key": "ed25519:GmfJ9ByRXANEHfB5w9QwGao6Uat6LyfWibZneyLeBBDp",
    "is_slashed": false,
    "stake": "121554041645655826532408602474",
    "shards": [
      0
    ],
    "num_produced_blocks": 99,
    "num_expected_blocks": 100
  },
  {
    "account_id": "jaroslavrud",
    "public_key": "ed25519:BYZQScWPwRxe7b7RqqreB38NzYtjzzbWX4rhme81G9Vm",
    "is_slashed": false,
    "stake": "116162105110155043864402750644",
    "shards": [
      0
    ],
    "num_produced_blocks": 99,
    "num_expected_blocks": 100
  },
  {
    "account_id": "joe1.joejoen.betanet",
    "public_key": "ed25519:4K31Dfc5Fm8HVrEJ485k7vyKqLrpXJAzmWk1D8Mp6tMe",
    "is_slashed": false,
    "stake": "89739186702781383982084648603",
    "shards": [
      0
    ],
    "num_produced_blocks": 0,
    "num_expected_blocks": 100
  },
  {
    "account_id": "launooskuarttu",
    "public_key": "ed25519:Frfpt7xwGyicxuGiH2KPy7pyhVMEou3a55CpvdDAiLQH",
    "is_slashed": false,
    "stake": "122194661649045549344009070977",
    "shards": [
      0
    ],
    "num_produced_blocks": 98,
    "num_expected_blocks": 100
  },
  {
    "account_id": "masternode24",
    "public_key": "ed25519:7GTm6xXJBFmPvuQXJeuaejwEQtpwnLocpM5eTUaQ8ckV",
    "is_slashed": false,
    "stake": "179653150228101560080882022934",
    "shards": [
      0
    ],
    "num_produced_blocks": 196,
    "num_expected_blocks": 200
  },
  {
    "account_id": "mathwallet",
    "public_key": "ed25519:2uBDxxQGP16XGHJHx9XeRtyZtdbUVWgKW2qiswQMZjcm",
    "is_slashed": false,
    "stake": "121631541622761990312608638357",
    "shards": [
      0
    ],
    "num_produced_blocks": 45,
    "num_expected_blocks": 100
  },
  {
    "account_id": "maxhealth",
    "public_key": "ed25519:6s8tx3VhwJkx9CusSSt7S4J8PmLRNDScmGF2gks12Rio",
    "is_slashed": false,
    "stake": "109627092426307627970086471299",
    "shards": [
      0
    ],
    "num_produced_blocks": 99,
    "num_expected_blocks": 100
  },
  {
    "account_id": "megatron",
    "public_key": "ed25519:5vhPUbWAeGHrsmS93QvrxSgTnZtEoWxYVpRpYYgsEmED",
    "is_slashed": false,
    "stake": "136837497342659400745298110909",
    "shards": [
      0
    ],
    "num_produced_blocks": 200,
    "num_expected_blocks": 200
  },
  {
    "account_id": "meleapool",
    "public_key": "ed25519:H6PAVhnKnp26gqQ1h5HwGVAvFB1ceaP3LFQwX6L8NSvY",
    "is_slashed": false,
    "stake": "119334452935885410668835668518",
    "shards": [
      0
    ],
    "num_produced_blocks": 98,
    "num_expected_blocks": 100
  },
  {
    "account_id": "mmm.stakehouse.betanet",
    "public_key": "ed25519:3wfTBqnMJAqvNnhyDqCP2e89yNaVgN9HFnoJnWu9GUue",
    "is_slashed": false,
    "stake": "127188986711535024064233853169",
    "shards": [
      0
    ],
    "num_produced_blocks": 195,
    "num_expected_blocks": 200
  },
  {
    "account_id": "olaiolsen",
    "public_key": "ed25519:sT5iqZ3WeFMKQx7sjcak4NnKBS3fKdLY2kAwzWi2uVP",
    "is_slashed": false,
    "stake": "122616284787722452592056777986",
    "shards": [
      0
    ],
    "num_produced_blocks": 99,
    "num_expected_blocks": 100
  },
  {
    "account_id": "olegjan",
    "public_key": "ed25519:2tapGm29zD71WKfvxRpRgMc3R7zv8iyM1eV6WYU6FE81",
    "is_slashed": false,
    "stake": "118373101076450674787468988238",
    "shards": [
      0
    ],
    "num_produced_blocks": 100,
    "num_expected_blocks": 100
  },
  {
    "account_id": "oligarr",
    "public_key": "ed25519:HqksthhKWmjAaiMLntcMz334TcdaADEWTQYoSYdtUrYs",
    "is_slashed": false,
    "stake": "118586416724485095022145289579",
    "shards": [
      0
    ],
    "num_produced_blocks": 100,
    "num_expected_blocks": 100
  },
  {
    "account_id": "optimisticvalidator",
    "public_key": "ed25519:frogMkugWJLmPvL1ZNKHK4g3q95r4tVfJj7KUDfw34S",
    "is_slashed": false,
    "stake": "88853598197016535383330822192",
    "shards": [
      0
    ],
    "num_produced_blocks": 100,
    "num_expected_blocks": 100
  },
  {
    "account_id": "ou812.stakehouse.betanet",
    "public_key": "ed25519:GbYBkPoR4vPq1etnXNKfxKZX6NjxL8P9Z9r7zJPnGoRG",
    "is_slashed": false,
    "stake": "109428868769492956653883389400",
    "shards": [
      0
    ],
    "num_produced_blocks": 98,
    "num_expected_blocks": 100
  },
  {
    "account_id": "plex2",
    "public_key": "ed25519:6qQ4kCneSDGumfQSZLRiFag34KypP9cmS5AYNKBUq22M",
    "is_slashed": false,
    "stake": "136790028949383760918621694921",
    "shards": [
      0
    ],
    "num_produced_blocks": 200,
    "num_expected_blocks": 201
  },
  {
    "account_id": "pool.bibiwang.betanet",
    "public_key": "ed25519:GWzkWkPJCyQPsHNtxoaU85anaatXyApqJe7S5G3jKZ19",
    "is_slashed": false,
    "stake": "91471771146578179309005958214",
    "shards": [
      0
    ],
    "num_produced_blocks": 97,
    "num_expected_blocks": 100
  },
  {
    "account_id": "pool.everstake.betanet",
    "public_key": "ed25519:9GpbeWAAV9Uopg8wQ48C6TTZH8etVSQzEPbKRsns2WDH",
    "is_slashed": false,
    "stake": "111871446611812863928736824752",
    "shards": [
      0
    ],
    "num_produced_blocks": 99,
    "num_expected_blocks": 100
  },
  {
    "account_id": "pool.zeropool.betanet",
    "public_key": "ed25519:FuzUe6pQDfHzkgJ8kbuZFrc845sToEaMbWqzHykgZbqy",
    "is_slashed": false,
    "stake": "116312505040040888735391549228",
    "shards": [
      0
    ],
    "num_produced_blocks": 99,
    "num_expected_blocks": 100
  },
  {
    "account_id": "poolz",
    "public_key": "ed25519:3Ym8oP47ZKAUmMYKVKHXp2feL3wDCSF14rVnuuJdHijU",
    "is_slashed": false,
    "stake": "110461261668161346364179312775",
    "shards": [
      0
    ],
    "num_produced_blocks": 99,
    "num_expected_blocks": 100
  },
  {
    "account_id": "pro.stakehouse.betanet",
    "public_key": "ed25519:6VGREgEwSEYqb2qbhjK8PvJc2NJKtdD9zy6RTbAccH3S",
    "is_slashed": false,
    "stake": "145350248131710422348805124771",
    "shards": [
      0
    ],
    "num_produced_blocks": 199,
    "num_expected_blocks": 200
  },
  {
    "account_id": "rockpathpool",
    "public_key": "ed25519:4GzkTonF8bFbjuBMxQe4ruQKuKKjUWtmXrSZ8XfyacNX",
    "is_slashed": false,
    "stake": "123122636218593847480323251496",
    "shards": [
      0
    ],
    "num_produced_blocks": 196,
    "num_expected_blocks": 200
  },
  {
    "account_id": "ryabina",
    "public_key": "ed25519:FLrYLCWPErGHTHg8mNfcXGHxaEpyAWB2ngjNytAyWXp8",
    "is_slashed": false,
    "stake": "117178715348189901177186219889",
    "shards": [
      0
    ],
    "num_produced_blocks": 100,
    "num_expected_blocks": 100
  },
  {
    "account_id": "sfpool",
    "public_key": "ed25519:HM8Rhkm3rnijhaVjfArc5G1fBiDRTW9tFeoZW5umrpxw",
    "is_slashed": false,
    "stake": "117572882537960944208698542708",
    "shards": [
      0
    ],
    "num_produced_blocks": 99,
    "num_expected_blocks": 100
  },
  {
    "account_id": "shudo",
    "public_key": "ed25519:6g1q7A5BZJKx8kNQiNXjLBkiW59h8Bp7cYQWAuk31QTS",
    "is_slashed": false,
    "stake": "65332456439917353900428069238",
    "shards": [
      0
    ],
    "num_produced_blocks": 99,
    "num_expected_blocks": 100
  },
  {
    "account_id": "simonhugo",
    "public_key": "ed25519:CuoBxwz8smgDZqYaW9TCo92v67Jn1Gu2xKyTfUhLcWGP",
    "is_slashed": false,
    "stake": "138990622209514766804386139406",
    "shards": [
      0
    ],
    "num_produced_blocks": 198,
    "num_expected_blocks": 200
  },
  {
    "account_id": "sl-he",
    "public_key": "ed25519:6bVNqQDFzKvFxnziQPoxmvTx9ojH4EAo873xSvaRVL9u",
    "is_slashed": false,
    "stake": "122412966611518872709922417148",
    "shards": [
      0
    ],
    "num_produced_blocks": 100,
    "num_expected_blocks": 100
  },
  {
    "account_id": "sl1sub",
    "public_key": "ed25519:EGCw1rG1LhVqRByDqiT7PC7QFwgrSMoP5PXTwDhrJXkb",
    "is_slashed": false,
    "stake": "130880679066075727905481933272",
    "shards": [
      0
    ],
    "num_produced_blocks": 198,
    "num_expected_blocks": 200
  },
  {
    "account_id": "sllpool",
    "public_key": "ed25519:DbjX97wwhzVTnkApwq8a7fZhBJ91VLv2iWtJEzhTFMnY",
    "is_slashed": false,
    "stake": "113799721522408219249215879082",
    "shards": [
      0
    ],
    "num_produced_blocks": 99,
    "num_expected_blocks": 100
  },
  {
    "account_id": "smart.askold.betanet",
    "public_key": "ed25519:7o4Pim8m4Ya7kSW42f9yeSk8BrnYRq98qsjTS3Wbjjsr",
    "is_slashed": false,
    "stake": "133698194492075514015890255237",
    "shards": [
      0
    ],
    "num_produced_blocks": 194,
    "num_expected_blocks": 200
  },
  {
    "account_id": "somebody",
    "public_key": "ed25519:GBWN5LhjL7jZN9PazMiwHZw6jWQSPNEsJCpXY1DJma2h",
    "is_slashed": false,
    "stake": "91373141058861198347146185607",
    "shards": [
      0
    ],
    "num_produced_blocks": 96,
    "num_expected_blocks": 100
  },
  {
    "account_id": "stake2earnfunds2",
    "public_key": "ed25519:AamXTuwhkcW8qPw1JhbcnHCEGTJ58C9XqnEJf2yuGerU",
    "is_slashed": false,
    "stake": "103452455910874463581120889923",
    "shards": [
      0
    ],
    "num_produced_blocks": 99,
    "num_expected_blocks": 100
  },
  {
    "account_id": "stakedpool.staked.test",
    "public_key": "ed25519:C7kGziRVKRPkx6Jjkc4Z2pQaAHikoN9ntx5QbxAgsy5s",
    "is_slashed": false,
    "stake": "133201581004910887031705539924",
    "shards": [
      0
    ],
    "num_produced_blocks": 200,
    "num_expected_blocks": 200
  },
  {
    "account_id": "stakery",
    "public_key": "ed25519:F6PoUtbtYBGJcfDpKaTycBL4GjpNk5qXAHGV9f2kMoKo",
    "is_slashed": false,
    "stake": "84441191639115509505017610797",
    "shards": [
      0
    ],
    "num_produced_blocks": 98,
    "num_expected_blocks": 100
  },
  {
    "account_id": "stakewolf_pool",
    "public_key": "ed25519:9Sv6QRWAoqE74H5W7WkRwuNhorKbSGbSZ8xEzDcpnZCi",
    "is_slashed": false,
    "stake": "104059499133213041894492653529",
    "shards": [
      0
    ],
    "num_produced_blocks": 99,
    "num_expected_blocks": 100
  },
  {
    "account_id": "stakin",
    "public_key": "ed25519:e8cQMCcQwow6zAEwfbUQAuysWjJPnN1bufLjof7uawi",
    "is_slashed": false,
    "stake": "127788335257955851941684596168",
    "shards": [
      0
    ],
    "num_produced_blocks": 198,
    "num_expected_blocks": 200
  },
  {
    "account_id": "sub1.crazylandd.betanet",
    "public_key": "ed25519:AGYymbNtSAjyDL9KPL9seaKt3bocq1n86jbmC2eTVQz5",
    "is_slashed": false,
    "stake": "111232443663630637242872383189",
    "shards": [
      0
    ],
    "num_produced_blocks": 97,
    "num_expected_blocks": 100
  },
  {
    "account_id": "swissqstakepoolsw3",
    "public_key": "ed25519:6KeKEp9fbdxVrxKVncqPEa4nUBD1rVgTxXyEwtjsstAc",
    "is_slashed": false,
    "stake": "90410831230096245520822714818",
    "shards": [
      0
    ],
    "num_produced_blocks": 99,
    "num_expected_blocks": 100
  },
  {
    "account_id": "tommywesley",
    "public_key": "ed25519:EZS7dMdmoDDmr6nKHuSx1aDrdvQQagsrsjEPStMV1yUe",
    "is_slashed": false,
    "stake": "118731100266419151134205718389",
    "shards": [
      0
    ],
    "num_produced_blocks": 98,
    "num_expected_blocks": 100
  },
  {
    "account_id": "valeraverim",
    "public_key": "ed25519:GmP7G7AECUZaeR3QW77PUz2oERisBbGQyDAqyK8Qi4Ei",
    "is_slashed": false,
    "stake": "91472135549893397962728120851",
    "shards": [
      0
    ],
    "num_produced_blocks": 97,
    "num_expected_blocks": 100
  },
  {
    "account_id": "validator.arno_nym.betanet",
    "public_key": "ed25519:3MsMrT5uMhfSds1o6uMGkVxqpT2Hug35TJ5VEA66Z3YN",
    "is_slashed": false,
    "stake": "102338444842810177266578355365",
    "shards": [
      0
    ],
    "num_produced_blocks": 33,
    "num_expected_blocks": 100
  },
  {
    "account_id": "validator_italia_contract",
    "public_key": "ed25519:HkchASewGKi7cHiif44mtB1xd3oxyxsNGd8sLgemKybP",
    "is_slashed": false,
    "stake": "111279393019620756699585634525",
    "shards": [
      0
    ],
    "num_produced_blocks": 98,
    "num_expected_blocks": 100
  },
  {
    "account_id": "villiamsivertsen",
    "public_key": "ed25519:BM2HyTL9T52gxp1MGcCZCjrDyKsWY6FmEffkWssdZn7u",
    "is_slashed": false,
    "stake": "119865268508232762154775494779",
    "shards": [
      0
    ],
    "num_produced_blocks": 98,
    "num_expected_blocks": 100
  },
  {
    "account_id": "vipstakes",
    "public_key": "ed25519:DmSyLLRR8zjCUiYNz8PRBQtmE4HbLVrzFoDJSk6zT9AK",
    "is_slashed": false,
    "stake": "108641816101050878594253357566",
    "shards": [
      0
    ],
    "num_produced_blocks": 100,
    "num_expected_blocks": 100
  },
  {
    "account_id": "wetez",
    "public_key": "ed25519:2PBULcGHiUovBne7WadfySqYNtg7eRbMgHMuXToDReLM",
    "is_slashed": false,
    "stake": "128324744763411511530889916999",
    "shards": [
      0
    ],
    "num_produced_blocks": 198,
    "num_expected_blocks": 200
  },
  {
    "account_id": "www.nodeasy.test",
    "public_key": "ed25519:JDi8eMdz9PVG1o7PB74B3Dyi34jrTSeocC8azoEadSLH",
    "is_slashed": false,
    "stake": "112973064085575621085649213855",
    "shards": [
      0
    ],
    "num_produced_blocks": 100,
    "num_expected_blocks": 100
  },
  {
    "account_id": "yoda",
    "public_key": "ed25519:CduMZVJ8AqkCYb38EGxZnCqgTCcE62p6HD4SFCPh2d2U",
    "is_slashed": false,
    "stake": "138230647353891060513345216724",
    "shards": [
      0
    ],
    "num_produced_blocks": 196,
    "num_expected_blocks": 200
  },
  {
    "account_id": "yyyyyyyyyyyyy1",
    "public_key": "ed25519:EP3xmkFhPcZwhuqacC7TibwbjhuyHd1JeiXU51gkde9n",
    "is_slashed": false,
    "stake": "109425621324909930269295733502",
    "shards": [
      0
    ],
    "num_produced_blocks": 100,
    "num_expected_blocks": 100
  },
  {
    "account_id": "zenqqqq",
    "public_key": "ed25519:8bR6a9bHCBWNRWGAs9gWWFrwtfD24CsTknNjHwhfdUAh",
    "is_slashed": false,
    "stake": "111939195893326593382822095550",
    "shards": [
      0
    ],
    "num_produced_blocks": 93,
    "num_expected_blocks": 100
  }
]